model_manager_test/__init__.py
model_manager_test/evaluator.py
model_manager_test/halo_profiling/__init__.py
model_manager_test/halo_profiling/sub_halp_profiling.py
model_manager_test/halo_validation/__init__.py
model_manager_test/halo_validation/sub_halo_validation.py
Model_Manager_Testing-0.0.1.dist-info/METADATA
Model_Manager_Testing-0.0.1.dist-info/WHEEL
Model_Manager_Testing-0.0.1.dist-info/top_level.txt
Model_Manager_Testing-0.0.1.dist-info/RECORD
