Metadata-Version: 2.1
Name: Model-Manager-Testing
Version: 0.0.1
Summary: Testing Purpose
Home-page: http://packages.python.org/an_example_pypi_project
Author: Balaji Chippada
Author-email: BALAJI.CHIPPADA@t-systems.com
License: BSD
Keywords: example documentation tutorial
Platform: UNKNOWN
Classifier: Development Status :: 3 - Alpha
Classifier: Topic :: Utilities
Classifier: License :: OSI Approved :: BSD License
Requires-Dist: pandas
Requires-Dist: numpy
